darkwood/__init__.py
darkwood/__main__.py
darkwood/client/__init__.py
darkwood/client/call.py
darkwood-1.0.8.dist-info/LICENSE
darkwood-1.0.8.dist-info/METADATA
darkwood-1.0.8.dist-info/WHEEL
darkwood-1.0.8.dist-info/entry_points.txt
darkwood-1.0.8.dist-info/top_level.txt
darkwood-1.0.8.dist-info/RECORD
