Metadata-Version: 2.1
Name: darkwood
Version: 1.0.8
Summary: Darkwood python client
Home-page: UNKNOWN
Author: Darkwood
Author-email: angelo@darkwood.tech
License: MIT
Platform: UNKNOWN
Classifier: License :: OSI Approved :: MIT License
Classifier: Programming Language :: Python :: 3
Classifier: Programming Language :: Python :: 3.7
Requires-Dist: requests
